<metadata xml:lang="de"><Esri><CreaDate>20160616</CreaDate><CreaTime>12275800</CreaTime><ArcGISFormat>1.0</ArcGISFormat><SyncOnce>TRUE</SyncOnce><ModDate>20170123</ModDate><ModTime>10472700</ModTime><scaleRange><minScale>150000000</minScale><maxScale>5000</maxScale></scaleRange><ArcGISProfile>ItemDescription</ArcGISProfile></Esri><dataIdInfo><idCitation><resTitle>HotSpot</resTitle></idCitation><idAbs>&lt;DIV STYLE="text-align:Left;"&gt;&lt;DIV&gt;&lt;DIV&gt;&lt;P&gt;&lt;SPAN&gt;Used to determine hotspots &lt;/SPAN&gt;&lt;SPAN&gt;defining high and low area of heat demand &lt;/SPAN&gt;&lt;SPAN&gt;in a given &lt;/SPAN&gt;&lt;SPAN&gt;town, region or &lt;/SPAN&gt;&lt;SPAN&gt;area of interest&lt;/SPAN&gt;&lt;/P&gt;&lt;/DIV&gt;&lt;/DIV&gt;&lt;/DIV&gt;</idAbs><searchKeys><keyword>Hotspot</keyword><keyword>Heat demand</keyword></searchKeys></dataIdInfo><distInfo><distributor><distorFormat><formatName>ArcToolbox Tool</formatName></distorFormat></distributor></distInfo><tool name="Tool" displayname="HotSpot" toolboxalias="" xmlns=""><parameters><param name="input1" displayname="Input Building Polygons" type="Required" direction="Input" datatype="Feature Layer" expression="input1"><dialogReference>&lt;DIV STYLE="text-align:Left;"&gt;&lt;DIV&gt;&lt;DIV&gt;&lt;P&gt;&lt;SPAN&gt;Input building polygon feature class. &lt;/SPAN&gt;&lt;/P&gt;&lt;P&gt;&lt;SPAN&gt;The feature class &lt;/SPAN&gt;&lt;SPAN&gt;must&lt;/SPAN&gt;&lt;SPAN /&gt;&lt;SPAN&gt;have &lt;/SPAN&gt;&lt;SPAN&gt;at least two &lt;/SPAN&gt;&lt;SPAN&gt;attribute&lt;/SPAN&gt;&lt;SPAN&gt;s&lt;/SPAN&gt;&lt;SPAN /&gt;&lt;SPAN STYLE="font-style:italic;"&gt;fun&lt;/SPAN&gt;&lt;SPAN STYLE="font-style:italic;"&gt;k&lt;/SPAN&gt;&lt;SPAN STYLE="font-style:italic;"&gt;tion &lt;/SPAN&gt;&lt;SPAN /&gt;&lt;SPAN STYLE="font-style:italic;"&gt;(i.e: building usage type) &lt;/SPAN&gt;&lt;SPAN&gt;and &lt;/SPAN&gt;&lt;SPAN STYLE="font-style:italic;"&gt;geschoss&lt;/SPAN&gt;&lt;SPAN /&gt;&lt;SPAN STYLE="font-style:italic;"&gt;(no.of storeys)&lt;/SPAN&gt;&lt;SPAN /&gt;&lt;SPAN&gt;for each building.&lt;/SPAN&gt;&lt;/P&gt;&lt;/DIV&gt;&lt;/DIV&gt;&lt;/DIV&gt;</dialogReference></param><param name="input6" displayname="Building Age Layer" type="Optional" direction="Input" datatype="Feature Layer" expression="{input6}"><dialogReference>&lt;DIV STYLE="text-align:Left;"&gt;&lt;DIV&gt;&lt;DIV&gt;&lt;P&gt;&lt;SPAN&gt;Heat demand of a building sometimes depend on building age (year of construction). It is especially significant for residential building types. A layer defining areas of the town with different building age group&lt;/SPAN&gt;&lt;SPAN&gt; is available&lt;/SPAN&gt;&lt;SPAN&gt;, it could be used to calculate more accurate hotspots. &lt;/SPAN&gt;&lt;/P&gt;&lt;P&gt;&lt;SPAN&gt;Input feature is a polygon layer with building age classes and corresponding heat demands. The age classes should be renamed as 'BAK' and heat demand as 'kWh_qm'. &lt;/SPAN&gt;&lt;/P&gt;&lt;/DIV&gt;&lt;/DIV&gt;&lt;/DIV&gt;</dialogReference></param><param name="out_features" displayname="Output Feature" type="Required" direction="Output" datatype="Feature Class" expression="out_features"><dialogReference>&lt;DIV STYLE="text-align:Left;"&gt;&lt;DIV&gt;&lt;P&gt;&lt;SPAN&gt;Generates a rasterized hotspot map with each cell (1oo sqm.) indicating the heat demand. &lt;/SPAN&gt;&lt;/P&gt;&lt;/DIV&gt;&lt;/DIV&gt;</dialogReference></param></parameters><arcToolboxHelpPath>c:\program files (x86)\arcgis\desktop10.3\Help\gp</arcToolboxHelpPath><summary>&lt;DIV STYLE="text-align:Left;"&gt;&lt;DIV&gt;&lt;DIV&gt;&lt;P&gt;&lt;SPAN&gt;Used to determine hotspots &lt;/SPAN&gt;&lt;SPAN&gt;defining high and low area of heat demand &lt;/SPAN&gt;&lt;SPAN&gt;in a given &lt;/SPAN&gt;&lt;SPAN&gt;town, region or &lt;/SPAN&gt;&lt;SPAN&gt;area of interest&lt;/SPAN&gt;&lt;/P&gt;&lt;/DIV&gt;&lt;/DIV&gt;&lt;/DIV&gt;</summary></tool><mdHrLv><ScopeCd value="005"/></mdHrLv></metadata>
